api/__init__.py
api/annotation.py
client/__init__.py
client/annotation_api_annotationset.py
client/annotation_client.py
config/__init__.py
config/arg_parser.py
config/config.py
datasink/__init__.py
datasink/csv_datasink.py
datasink/filename_provider.py
datasource/__init__.py
datasource/image_datasource.py
datasource/mongo_query_pipeline.py
datasource/sharded_mongo_datasource.py
datasource/xml_datasource.py
operator/__init__.py
operator/archiver.py
operator/cityscapes_formatter.py
operator/coco_formatter.py
operator/cvat_formatter.py
operator/filter.py
operator/image_formatter.py
operator/imagenet_formatter.py
operator/infer.py
operator/label_formatter.py
operator/model_operator.py
operator/paddleclas_formatter.py
operator/paddleseg_formatter.py
operator/reader.py
operator/thumbnail_generator.py
operator/vistudio_cutter.py
operator/vistudio_formatter.py
operator/webp_generator.py
operator/webp_state_updater.py
operator/zip_formatter.py
operator/updater/__init__.py
operator/updater/annotation_state_updater.py
operator/updater/base_mongo_updater.py
operator/updater/image_created_at_updater.py
operator/updater/thumbnail_state_updater.py
operator/updater/webp_state_updater.py
pipeline/__init__.py
pipeline/base.py
pipeline/base_export_pipeline.py
pipeline/base_import_pipeline.py
pipeline/base_infer_pipeline.py
pipeline/batch_delete.py
pipeline/batch_infer_pipeline.py
pipeline/batch_update.py
pipeline/export_coco_pipeline.py
pipeline/export_paddleclas_pipeline.py
pipeline/export_paddleseg_pipeline.py
pipeline/factory.py
pipeline/generate_thumbnail_pipeline.py
pipeline/generate_webp_pipeline.py
pipeline/import_cityscapes_pipeline.py
pipeline/import_coco_pipeline.py
pipeline/import_cvat_pipeline.py
pipeline/import_imagenet_pipeline.py
pipeline/import_vistudio_pipeline.py
pipeline/query_pipeline.py
pipeline/statistic.py
pipeline/update_annotation_state_pipeline.py
pipeline/update_image_created_at_pipeline.py
processor/__init__.py
processor/cutter/__init__.py
vistudio_image_analysis-1.0.0.1.dist-info/METADATA
vistudio_image_analysis-1.0.0.1.dist-info/WHEEL
vistudio_image_analysis-1.0.0.1.dist-info/top_level.txt
vistudio_image_analysis-1.0.0.1.dist-info/RECORD
